numerous/apps/__init__.py
numerous/apps/app_factory.py
numerous/apps/bootstrap.py
numerous/apps/builtins.py
numerous/apps/communication.py
numerous/apps/execution.py
numerous/apps/models.py
numerous/apps/multi_app.py
numerous/apps/server.py
numerous/apps/session_management.py
numerous/apps/auth/__init__.py
numerous/apps/auth/base.py
numerous/apps/auth/dependencies.py
numerous/apps/auth/exceptions.py
numerous/apps/auth/jwt_utils.py
numerous/apps/auth/middleware.py
numerous/apps/auth/models.py
numerous/apps/auth/routes.py
numerous/apps/auth/providers/__init__.py
numerous/apps/auth/providers/database_auth.py
numerous/apps/auth/providers/env_auth.py
numerous/apps/bootstrap_app/.gitignore
numerous/apps/bootstrap_app/Dockerfile
numerous/apps/bootstrap_app/app.py
numerous/apps/bootstrap_app/app_cover.jpg
numerous/apps/bootstrap_app/index.html.j2
numerous/apps/bootstrap_app/numerous.toml
numerous/apps/bootstrap_app/requirements.txt
numerous/apps/bootstrap_app/static/logo.svg
numerous/apps/bootstrap_app/static/css/styles.css
numerous/apps/bootstrap_app/widgets/__init__.py
numerous/apps/bootstrap_app/widgets/charts.py
numerous/apps/js/auth.js
numerous/apps/js/numerous.js
numerous/apps/js/parent_visibility.js
numerous/apps/static/README.md
numerous/apps/static/css/numerous-base.css
numerous/apps/templates/app_process_error.html.j2
numerous/apps/templates/error.html.j2
numerous/apps/templates/error_modal.html.j2
numerous/apps/templates/login.html.j2
numerous/apps/templates/session_lost_banner.html.j2
numerous/apps/templates/splash_screen.html.j2
numerous_apps-0.6.2.dist-info/licenses/LICENSE.md
numerous_apps-0.6.2.dist-info/METADATA
numerous_apps-0.6.2.dist-info/WHEEL
numerous_apps-0.6.2.dist-info/entry_points.txt
numerous_apps-0.6.2.dist-info/top_level.txt
numerous_apps-0.6.2.dist-info/RECORD
