Metadata-Version: 2.4
Name: numerous-apps
Version: 0.6.2
Summary: Application package for numerous
Author-email: Lasse Thomsen <lasse.thomsen@numerous.com>
License: MIT
Project-URL: Homepage, https://github.com/numerous-com/numerous-app
Project-URL: Repository, https://github.com/numerous-com/numerous-app
Classifier: Programming Language :: Python :: 3
Classifier: Development Status :: 2 - Pre-Alpha
Classifier: Intended Audience :: Developers
Requires-Python: >=3.12
License-File: LICENSE.md
Requires-Dist: fastapi==0.115.6
Requires-Dist: uvicorn[standard]==0.32.1
Requires-Dist: jinja2==3.1.4
Requires-Dist: anywidget==0.9.13
Requires-Dist: numpy>=2.0.0
Requires-Dist: pydantic==2.10.3
Requires-Dist: PyJWT>=2.8.0
Provides-Extra: auth-db
Requires-Dist: sqlalchemy[asyncio]>=2.0.0; extra == "auth-db"
Requires-Dist: asyncpg>=0.29.0; extra == "auth-db"
Requires-Dist: aiosqlite>=0.19.0; extra == "auth-db"
Requires-Dist: bcrypt>=4.1.0; extra == "auth-db"
Provides-Extra: dev
Requires-Dist: anywidget[dev]==0.9.13; extra == "dev"
Requires-Dist: python-dotenv==1.0.1; extra == "dev"
Requires-Dist: numerous-widgets; extra == "dev"
Requires-Dist: numpy>=2.0.0; extra == "dev"
Requires-Dist: pytest==8.3.4; extra == "dev"
Requires-Dist: ruff==0.6.4; extra == "dev"
Requires-Dist: mypy==1.11.2; extra == "dev"
Requires-Dist: coverage==7.6.1; extra == "dev"
Requires-Dist: twine==5.1.1; extra == "dev"
Requires-Dist: mkdocs==1.6.0; extra == "dev"
Requires-Dist: mkdocstrings==0.26.2; extra == "dev"
Requires-Dist: mkdocstrings-python==1.12.2; extra == "dev"
Requires-Dist: mkdocs_snippet_plugin==1.0.2; extra == "dev"
Requires-Dist: pre-commit==4.0.1; extra == "dev"
Requires-Dist: black==24.10.0; extra == "dev"
Requires-Dist: mkdocs-material==9.5.46; extra == "dev"
Requires-Dist: mkdocs-gen-files==0.5.0; extra == "dev"
Requires-Dist: mkdocs-section-index==0.3.9; extra == "dev"
Requires-Dist: mkdocs-literate-nav==0.6.1; extra == "dev"
Requires-Dist: marimo==0.10.7; extra == "dev"
Requires-Dist: panel==1.5.5; extra == "dev"
Requires-Dist: pytest-cov==4.1.0; extra == "dev"
Requires-Dist: httpx==0.28.1; extra == "dev"
Requires-Dist: pytest-asyncio==0.25.2; extra == "dev"
Requires-Dist: playwright==1.49.1; extra == "dev"
Requires-Dist: psutil==6.1.1; extra == "dev"
Dynamic: license-file
